PySparkMLtoolbox/__init__.py
PySparkMLtoolbox/fuzzyclustering/Algorithm.py
PySparkMLtoolbox/fuzzyclustering/ClusterAidedComputing.py
PySparkMLtoolbox/fuzzyclustering/ClusteringIteration.py
PySparkMLtoolbox/fuzzyclustering/__init__.py
PySparkMLtoolbox/fuzzyclustering/rddtoarray.py
PySparkMLtoolbox-0.0.1.dist-info/LICENSE.txt
PySparkMLtoolbox-0.0.1.dist-info/METADATA
PySparkMLtoolbox-0.0.1.dist-info/WHEEL
PySparkMLtoolbox-0.0.1.dist-info/top_level.txt
PySparkMLtoolbox-0.0.1.dist-info/RECORD
